queryStringParser/__init__.py
queryStringParser/src/__init__.py
queryStringParser/src/parser.py
tests/__init__.py
tests/main.py
Query_string_parser-1.0.0.dist-info/LICENSE
Query_string_parser-1.0.0.dist-info/LICENSE.txt
Query_string_parser-1.0.0.dist-info/METADATA
Query_string_parser-1.0.0.dist-info/WHEEL
Query_string_parser-1.0.0.dist-info/top_level.txt
Query_string_parser-1.0.0.dist-info/RECORD
