Metadata-Version: 2.1
Name: Query-string-parser
Version: 1.0.0
Summary: Query string parser like php
Home-page: https://github.com/coloombus/query-string-parser.git
Author: Riccardo Curcio
Author-email: rcurcio@coloombus.com
License: GPL v3
Download-URL: https://github.com/coloombus/query-string-parser/archive/develop.zip
Keywords: query string,http,coloombus
Platform: UNKNOWN
Classifier: Programming Language :: Python :: 3
Classifier: License :: OSI Approved :: GNU General Public License v3 (GPLv3)
Classifier: Operating System :: OS Independent
Requires-Python: >=3.6
Requires-Dist: typing
Requires-Dist: querystring-parser
Requires-Dist: OrderedDict
